django_sphinx_hosting-1.7.1.dist-info/licenses/LICENSE.txt
doc/source/conf.py
sandbox/manage.py
sandbox/demo/__init__.py
sandbox/demo/gunicorn_config.py
sandbox/demo/logging.py
sandbox/demo/settings.py
sandbox/demo/settings_docker.py
sandbox/demo/urls.py
sandbox/demo/wsgi.py
sandbox/demo/core/__init__.py
sandbox/demo/core/admin.py
sandbox/demo/core/apps.py
sandbox/demo/core/forms.py
sandbox/demo/core/models.py
sandbox/demo/core/tests.py
sandbox/demo/core/urls.py
sandbox/demo/core/views.py
sandbox/demo/core/wildewidgets.py
sandbox/demo/core/management/commands/__init__.py
sandbox/demo/core/management/commands/bootstrap.py
sandbox/demo/core/migrations/__init__.py
sandbox/demo/users/__init__.py
sandbox/demo/users/apps.py
sandbox/demo/users/models.py
sandbox/demo/users/tests.py
sandbox/demo/users/management/__init__.py
sandbox/demo/users/management/commands/__init__.py
sandbox/demo/users/management/commands/list_api_users.py
sandbox/demo/users/management/commands/manage_api_user.py
sandbox/demo/users/migrations/0001_initial.py
sandbox/demo/users/migrations/0002_load_fixture.py
sandbox/demo/users/migrations/0003_api_group.py
sandbox/demo/users/migrations/0004_apiuser.py
sandbox/demo/users/migrations/0005_api_user_permissions.py
sandbox/demo/users/migrations/__init__.py
sandbox/etc/ipython_config.py
sphinx_hosting/__init__.py
sphinx_hosting/apps.py
sphinx_hosting/exc.py
sphinx_hosting/fields.py
sphinx_hosting/form_fields.py
sphinx_hosting/forms.py
sphinx_hosting/importers.py
sphinx_hosting/logging.py
sphinx_hosting/models.py
sphinx_hosting/py.typed
sphinx_hosting/search_indexes.py
sphinx_hosting/settings.py
sphinx_hosting/signals.py
sphinx_hosting/types.py
sphinx_hosting/urls.py
sphinx_hosting/validators.py
sphinx_hosting/views.py
sphinx_hosting/api/__init__.py
sphinx_hosting/api/apps.py
sphinx_hosting/api/permissions.py
sphinx_hosting/api/serializers.py
sphinx_hosting/api/urls.py
sphinx_hosting/api/views.py
sphinx_hosting/fixtures/classifiers.json
sphinx_hosting/management/__init__.py
django_sphinx_hosting-1.7.1.dist-info/METADATA
django_sphinx_hosting-1.7.1.dist-info/WHEEL
django_sphinx_hosting-1.7.1.dist-info/top_level.txt
django_sphinx_hosting-1.7.1.dist-info/RECORD
