Metadata-Version: 2.4
Name: django-sphinx-hosting
Version: 1.7.1
Summary: Reusable Django app for hosting Sphinx documentation privately.
Author-email: Caltech IMSS ADS <imss-ads-staff@caltech.edu>
Maintainer-email: Chris Malek <cmalek@caltech.edu>
Project-URL: Documentation, https://django-sphinx-hosting.readthedocs.io/en/latest/
Project-URL: Source, https://github.com/caltechads/django-sphinx-hosting
Project-URL: Issues, https://github.com/caltechads/django-sphinx-hosting/issues
Keywords: documentation,sphinx,django
Classifier: Development Status :: 4 - Beta
Classifier: Intended Audience :: Developers
Classifier: Operating System :: OS Independent
Classifier: Programming Language :: Python
Classifier: Programming Language :: Python :: 3
Classifier: Programming Language :: Python :: 3.9
Classifier: Programming Language :: Python :: 3.11
Classifier: Programming Language :: Python :: 3.12
Classifier: Framework :: Django :: 3.2
Classifier: Framework :: Django :: 4.0
Classifier: Framework :: Django :: 4.1
Classifier: Framework :: Django :: 4.2
Classifier: Framework :: Django :: 5.0
Classifier: Framework :: Django :: 5.1
Classifier: Framework :: Django :: 5.2
Classifier: Topic :: Documentation :: Sphinx
Classifier: Topic :: Software Development :: Documentation
Requires-Python: >=3.11
License-File: LICENSE.txt
Requires-Dist: django>=4.2
Requires-Dist: django-braces>=1.15.0
Requires-Dist: django-crispy-forms>=2.3
Requires-Dist: django-extensions>=3.2.3
Requires-Dist: django-filter>=24.2
Requires-Dist: django-haystack>=3.3.0
Requires-Dist: django-rest-framework-helpers>=8.5.0
Requires-Dist: django-theme-academy>=0.3.11
Requires-Dist: django-wildewidgets>=1.2.3
Requires-Dist: djangorestframework>=3.15.2
Requires-Dist: drf-spectacular>=0.27.2
Requires-Dist: crispy-bootstrap5>=2024.10
Requires-Dist: semver>=3.0.2
Requires-Dist: humanize>=4.11.0
Requires-Dist: lxml>=4.9.1
Requires-Dist: cssselect>=1.2.0
Requires-Dist: rich>=13.9.4
Dynamic: license-file
